bwt_scrapy_proxy/__init__.py
bwt_scrapy_proxy-0.1.0.dist-info/LICENSE
bwt_scrapy_proxy-0.1.0.dist-info/METADATA
bwt_scrapy_proxy-0.1.0.dist-info/WHEEL
bwt_scrapy_proxy-0.1.0.dist-info/top_level.txt
bwt_scrapy_proxy-0.1.0.dist-info/RECORD
